lesscode_flask/__init__.py
lesscode_flask/app.py
lesscode_flask/signals.py
lesscode_flask/wsgi.py
lesscode_flask/db/__init__.py
lesscode_flask/db/datasource.py
lesscode_flask/db/executor.py
lesscode_flask/export_data/__init__.py
lesscode_flask/export_data/data_download_handler.py
lesscode_flask/log/access_log_handler.py
lesscode_flask/model/access_log.py
lesscode_flask/model/base_model.py
lesscode_flask/model/parameterized_query.py
lesscode_flask/model/resource_param_template.py
lesscode_flask/model/response_result.py
lesscode_flask/model/user.py
lesscode_flask/model/user_limit_policy.py
lesscode_flask/service/access_log_service.py
lesscode_flask/service/base_service.py
lesscode_flask/service/resource_param_template_service.py
lesscode_flask/setting/__init__.py
lesscode_flask/setup/__init__.py
lesscode_flask/static/swagger.py
lesscode_flask/utils/dify_utils.py
lesscode_flask/utils/fs_util.py
lesscode_flask/utils/helpers.py
lesscode_flask/utils/decorator/__init__.py
lesscode_flask/utils/decorator/cache.py
lesscode_flask/utils/decorator/sql_injection.py
lesscode_flask/utils/decorator/swagger.py
lesscode_flask/utils/file/file_exporter.py
lesscode_flask/utils/file/file_utils.py
lesscode_flask/utils/json/NotSortJSONProvider.py
lesscode_flask/utils/limit/__init__.py
lesscode_flask/utils/limit/limit_util.py
lesscode_flask/utils/limit/consecutive/consecutive_limiter_handler.py
lesscode_flask/utils/limit/consecutive/redis_consecutive_limiter.py
lesscode_flask/utils/limit/req/rate_limiter_handler.py
lesscode_flask/utils/limit/req/redis_rate_limiter.py
lesscode_flask/utils/limit/req_count/count_limiter_handler.py
lesscode_flask/utils/limit/req_count/redis_count_limiter.py
lesscode_flask/utils/oss/__init__.py
lesscode_flask/utils/oss/aliyun_oss.py
lesscode_flask/utils/oss/ks3_oss.py
lesscode_flask/utils/oss/minio_oss.py
lesscode_flask/utils/redis/redis_helper.py
lesscode_flask/utils/request/request.py
lesscode_flask/utils/swagger/swagger_template.py
lesscode_flask-0.2.52.dist-info/METADATA
lesscode_flask-0.2.52.dist-info/WHEEL
lesscode_flask-0.2.52.dist-info/top_level.txt
lesscode_flask-0.2.52.dist-info/RECORD
