Metadata-Version: 2.4
Name: lesscode-flask
Version: 0.2.52
Summary: lesscode-flask 是基于flask的web开发脚手架项目，该项目初衷为简化开发过程，让研发人员更加关注业务。
Home-page: https://lesscode-flask
Author: Chao.yy
Author-email: yuyc@ishangqi.com
Platform: python
Classifier: Programming Language :: Python :: 3
Classifier: Operating System :: OS Independent
Requires-Python: >=3.9
Requires-Dist: Flask==3.0.3
Requires-Dist: lesscode-utils==0.0.91
Requires-Dist: Flask-Login==0.6.3
Requires-Dist: redis==5.1.1
Requires-Dist: flask-swagger-ui==4.11.1
Requires-Dist: pystache==0.6.5
Requires-Dist: python-dateutil==2.9.0.post0
Requires-Dist: funcy==2.0
Requires-Dist: Flask-SQLAlchemy==3.1.1
Requires-Dist: sqlparse==0.5.1
Requires-Dist: requests==2.32.3
Requires-Dist: gunicorn==23.0.0
Requires-Dist: gevent==25.5.1
Requires-Dist: openpyxl==3.1.5
Requires-Dist: iputil==0.3.1
Requires-Dist: phone==0.4.5
Dynamic: author
Dynamic: author-email
Dynamic: classifier
Dynamic: description
Dynamic: description-content-type
Dynamic: home-page
Dynamic: platform
Dynamic: requires-dist
Dynamic: requires-python
Dynamic: summary
